{
	"archive" : {},
	"artifacts" : 
	[
		{
			"path" : "VINS-Mobile-master/ThirdParty/DUtils/libDUtils.a"
		}
	],
	"backtrace" : 1,
	"backtraceGraph" : 
	{
		"commands" : 
		[
			"add_library",
			"include_directories"
		],
		"files" : 
		[
			"VINS-Mobile-master/ThirdParty/DUtils/CMakeLists.txt",
			"CMakeLists.txt"
		],
		"nodes" : 
		[
			{
				"file" : 0
			},
			{
				"command" : 0,
				"file" : 0,
				"line" : 17,
				"parent" : 0
			},
			{
				"file" : 1
			},
			{
				"command" : 1,
				"file" : 1,
				"line" : 13,
				"parent" : 2
			}
		]
	},
	"compileGroups" : 
	[
		{
			"compileCommandFragments" : 
			[
				{
					"fragment" : "-g"
				},
				{
					"fragment" : "-std=gnu++11"
				}
			],
			"includes" : 
			[
				{
					"backtrace" : 3,
					"path" : "/home/dorian/w/dev_panel"
				}
			],
			"language" : "CXX",
			"languageStandard" : 
			{
				"backtraces" : 
				[
					1
				],
				"standard" : "11"
			},
			"sourceIndexes" : 
			[
				0,
				1
			]
		}
	],
	"id" : "DUtils::@1b27374b10b33b4b6379",
	"name" : "DUtils",
	"nameOnDisk" : "libDUtils.a",
	"paths" : 
	{
		"build" : "VINS-Mobile-master/ThirdParty/DUtils",
		"source" : "VINS-Mobile-master/ThirdParty/DUtils"
	},
	"sourceGroups" : 
	[
		{
			"name" : "Source Files",
			"sourceIndexes" : 
			[
				0,
				1
			]
		}
	],
	"sources" : 
	[
		{
			"backtrace" : 1,
			"compileGroupIndex" : 0,
			"path" : "VINS-Mobile-master/ThirdParty/DUtils/Timestamp.cpp",
			"sourceGroupIndex" : 0
		},
		{
			"backtrace" : 1,
			"compileGroupIndex" : 0,
			"path" : "VINS-Mobile-master/ThirdParty/DUtils/Random.cpp",
			"sourceGroupIndex" : 0
		}
	],
	"type" : "STATIC_LIBRARY"
}
